boto3_utility_belt/__init__.py
boto3_utility_belt/awsconfig.py
boto3_utility_belt/console.py
boto3_utility_belt/get_all_saml_creds.py
boto3_utility_belt/organizations.py
boto3_utility_belt/refresher.py
boto3_utility_belt/sessions.py
boto3_utility_belt-0.1.0.dist-info/LICENSE
boto3_utility_belt-0.1.0.dist-info/WHEEL
boto3_utility_belt-0.1.0.dist-info/METADATA
boto3_utility_belt-0.1.0.dist-info/RECORD
